docs/01.Embedding.ipynb
docs/02.ClinVarVariantPredict.ipynb
docs/03.RNASeqConvTrack.ipynb
docs/Makefile
docs/api.rst
docs/conf.py
docs/index.rst
docs/installation.rst
docs/reference.rst
docs/release.md
docs/_autosummary/genos.api.embedding_extractor.rst
docs/_autosummary/genos.api.health.rst
docs/_autosummary/genos.api.rst
docs/_autosummary/genos.api.variant_predictor.rst
docs/_autosummary/genos.client.rst
docs/_static/geno.png
genos/__init__.py
genos/client.py
genos/config.py
genos/exceptions.py
genos/api/__init__.py
genos/api/embedding_extractor.py
genos/api/health.py
genos/api/rna_seq_coverage_track_prediction.py
genos/api/variant_predictor.py
genos/data/gencode.v48.annotation.gff3.gz
genos/plots/__init__.py
genos/plots/genomic_track_viewer.py
genos/utils/__init__.py
genos/utils/genomic_track_utils.py
genos_client-0.1.2.dist-info/LICENSE
genos_client-0.1.2.dist-info/METADATA
genos_client-0.1.2.dist-info/WHEEL
genos_client-0.1.2.dist-info/top_level.txt
genos_client-0.1.2.dist-info/RECORD
