Metadata-Version: 2.1
Name: genos-client
Version: 0.1.2
Summary: Genos API client for accessing genomic analysis services
Author-email: Genos Team <Genos@genomics.cn>
Maintainer-email: qiuping1 <qiuping1@genomics.cn>, chenjunhong <chenjunhong@genomics.cn>, tianyongjing <tianyongjing@genomics.cn>
License: MIT
Project-URL: Homepage, https://github.com/BGI-HangzhouAI/Genos
Project-URL: Documentation, https://genos-client.readthedocs.io/
Project-URL: Source, https://github.com/BGI-HangzhouAI/Genos/tree/main/sdk
Project-URL: Issues, https://github.com/BGI-HangzhouAI/Genos/issues
Keywords: genomics,variant,prediction,api,client,visualization
Classifier: Programming Language :: Python :: 3
Classifier: Operating System :: OS Independent
Classifier: Intended Audience :: Science/Research
Classifier: Topic :: Scientific/Engineering :: Bio-Informatics
Requires-Python: >=3.10
License-File: LICENSE
Requires-Dist: requests
Requires-Dist: numpy
Requires-Dist: matplotlib
Requires-Dist: pandas
Requires-Dist: pyfaidx
Requires-Dist: pyBigWig
Requires-Dist: torch
Provides-Extra: dev
Requires-Dist: black ; extra == 'dev'
Requires-Dist: pytest ; extra == 'dev'
Requires-Dist: flake8 ; extra == 'dev'
Provides-Extra: viz
Requires-Dist: matplotlib ; extra == 'viz'
Requires-Dist: pandas ; extra == 'viz'
